{
  "type": "carousel",
  "contents": [
    {
      "type": "bubble",
      "body": {
        "type": "box",
        "layout": "vertical",
        "contents": [
          {
            "type": "image",
            "url": "https://cdn.corporatefinanceinstitute.com/assets/day-trader-1024x683.jpeg",
            "size": "full",
            "aspectMode": "cover",
            "aspectRatio": "2:3",
            "gravity": "top",
            "animated": false
          },
          {
            "type": "box",
            "layout": "vertical",
            "contents": [
              {
                "type": "box",
                "layout": "vertical",
                "contents": [
                  {
                    "type": "text",
                    "text": "Oil Trader \n",
                    "size": "xl",
                    "color": "#ffffff",
                    "weight": "bold",
                    "wrap": true
                  }
                ]
              },
              {
                "type": "box",
                "layout": "baseline",
                "contents": [
                  {
                    "type": "text",
                    "text": "$120,008/Yr",
                    "color": "#ebebeb",
                    "size": "sm",
                    "flex": 0
                  }
                ],
                "spacing": "lg"
              },
              {
                "type": "box",
                "layout": "vertical",
                "contents": [
                  {
                    "type": "filler"
                  },
                  {
                    "type": "box",
                    "layout": "baseline",
                    "action": {
                      "type": "message",
                      "label": "action",
                      "text": "I would like to be an Oil Trader"
                    },
                    "contents": [
                      {
                        "type": "filler"
                      },
                      {
                        "type": "text",
                        "text": "Let's Go",
                        "color": "#ffffff",
                        "flex": 0,
                        "offsetTop": "-2px"
                      },
                      {
                        "type": "filler"
                      }
                    ],
                    "spacing": "sm"
                  },
                  {
                    "type": "filler"
                  }
                ],
                "borderWidth": "1px",
                "cornerRadius": "4px",
                "spacing": "sm",
                "borderColor": "#ffffff",
                "margin": "xxl",
                "height": "40px"
              }
            ],
            "position": "absolute",
            "offsetBottom": "0px",
            "offsetStart": "0px",
            "offsetEnd": "0px",
            "paddingAll": "20px",
            "paddingTop": "18px",
            "backgroundColor": "#03303Acc"
          },
          {
            "type": "box",
            "layout": "vertical",
            "contents": [
              {
                "type": "text",
                "text": "HOT",
                "color": "#ffffff",
                "align": "center",
                "size": "xs",
                "offsetTop": "6px"
              }
            ],
            "position": "absolute",
            "cornerRadius": "20px",
            "offsetTop": "18px",
            "backgroundColor": "#ff334b",
            "offsetStart": "18px",
            "height": "25px",
            "width": "53px"
          }
        ],
        "paddingAll": "0px"
      }
    },
    {
      "type": "bubble",
      "body": {
        "type": "box",
        "layout": "vertical",
        "contents": [
          {
            "type": "image",
            "url": "https://shooliniuniversity.com/blog/wp-content/uploads/2023/08/How-to-Become-a-Better-Coder.png",
            "size": "full",
            "aspectMode": "cover",
            "aspectRatio": "2:3",
            "gravity": "top"
          },
          {
            "type": "box",
            "layout": "vertical",
            "contents": [
              {
                "type": "box",
                "layout": "vertical",
                "contents": [
                  {
                    "type": "text",
                    "text": "Full Stack Developer \n",
                    "size": "xl",
                    "color": "#ffffff",
                    "weight": "bold",
                    "wrap": true
                  }
                ]
              },
              {
                "type": "box",
                "layout": "baseline",
                "contents": [
                  {
                    "type": "text",
                    "text": "$90,000/Yr",
                    "color": "#ebebeb",
                    "size": "sm",
                    "flex": 0
                  }
                ],
                "spacing": "lg"
              },
              {
                "type": "box",
                "layout": "vertical",
                "action": {
                  "type": "message",
                  "label": "action",
                  "text": "I would like to be a Full Stack Developer"
                },
                "contents": [
                  {
                    "type": "filler"
                  },
                  {
                    "type": "box",
                    "layout": "baseline",
                    "contents": [
                      {
                        "type": "filler"
                      },
                      {
                        "type": "text",
                        "text": "Let's Go",
                        "color": "#ffffff",
                        "flex": 0,
                        "offsetTop": "-2px"
                      },
                      {
                        "type": "filler"
                      }
                    ],
                    "spacing": "sm"
                  },
                  {
                    "type": "filler"
                  }
                ],
                "borderWidth": "1px",
                "cornerRadius": "4px",
                "spacing": "sm",
                "borderColor": "#ffffff",
                "margin": "xxl",
                "height": "40px"
              }
            ],
            "position": "absolute",
            "offsetBottom": "0px",
            "offsetStart": "0px",
            "offsetEnd": "0px",
            "backgroundColor": "#9C8E7Ecc",
            "paddingAll": "20px",
            "paddingTop": "18px"
          },
          {
            "type": "box",
            "layout": "vertical",
            "contents": [
              {
                "type": "text",
                "text": "HOT",
                "color": "#ffffff",
                "align": "center",
                "size": "xs",
                "offsetTop": "6px"
              }
            ],
            "position": "absolute",
            "cornerRadius": "20px",
            "offsetTop": "18px",
            "backgroundColor": "#ff334b",
            "offsetStart": "18px",
            "height": "25px",
            "width": "53px"
          }
        ],
        "paddingAll": "0px"
      }
    },
    {
      "type": "bubble",
      "body": {
        "type": "box",
        "layout": "vertical",
        "contents": [
          {
            "type": "image",
            "url": "https://study-eu.s3.amazonaws.com/uploads/image/path/684/wide_fullhd_study-education-teaching.jpg",
            "size": "full",
            "aspectMode": "cover",
            "aspectRatio": "2:3",
            "gravity": "top",
            "animated": false
          },
          {
            "type": "box",
            "layout": "vertical",
            "contents": [
              {
                "type": "box",
                "layout": "vertical",
                "contents": [
                  {
                    "type": "text",
                    "text": "Teacher \n",
                    "size": "xl",
                    "color": "#ffffff",
                    "weight": "bold",
                    "wrap": true
                  }
                ]
              },
              {
                "type": "box",
                "layout": "baseline",
                "contents": [
                  {
                    "type": "text",
                    "text": "$120,008/Yr",
                    "color": "#ebebeb",
                    "size": "sm",
                    "flex": 0
                  }
                ],
                "spacing": "lg"
              },
              {
                "type": "box",
                "layout": "vertical",
                "contents": [
                  {
                    "type": "filler"
                  },
                  {
                    "type": "box",
                    "layout": "baseline",
                    "action": {
                      "type": "message",
                      "label": "action",
                      "text": "I would like to be an Teacher"
                    },
                    "contents": [
                      {
                        "type": "filler"
                      },
                      {
                        "type": "text",
                        "text": "Let's Go",
                        "color": "#ffffff",
                        "flex": 0,
                        "offsetTop": "-2px"
                      },
                      {
                        "type": "filler"
                      }
                    ],
                    "spacing": "sm"
                  },
                  {
                    "type": "filler"
                  }
                ],
                "borderWidth": "1px",
                "cornerRadius": "4px",
                "spacing": "sm",
                "borderColor": "#ffffff",
                "margin": "xxl",
                "height": "40px"
              }
            ],
            "position": "absolute",
            "offsetBottom": "0px",
            "offsetStart": "0px",
            "offsetEnd": "0px",
            "paddingAll": "20px",
            "paddingTop": "18px",
            "backgroundColor": "#A0522D99"
          }
        ],
        "paddingAll": "0px"
      }
    },
    {
      "type": "bubble",
      "body": {
        "type": "box",
        "layout": "vertical",
        "contents": [
          {
            "type": "image",
            "url": "https://assets.entrepreneur.com/content/3x2/2000/20181031185622-shutterstock-1140699056-crop.jpeg",
            "size": "full",
            "aspectMode": "cover",
            "aspectRatio": "2:3",
            "gravity": "top",
            "animated": false
          },
          {
            "type": "box",
            "layout": "vertical",
            "contents": [
              {
                "type": "box",
                "layout": "vertical",
                "contents": [
                  {
                    "type": "text",
                    "text": "Sales Development Representative",
                    "size": "xl",
                    "color": "#ffffff",
                    "weight": "bold",
                    "wrap" : true
                  }
                ]
              },
              {
                "type": "box",
                "layout": "baseline",
                "contents": [
                  {
                    "type": "text",
                    "text": "$91,500/Yr",
                    "color": "#ebebeb",
                    "size": "sm",
                    "flex": 0
                  }
                ],
                "spacing": "lg"
              },
              {
                "type": "box",
                "layout": "vertical",
                "action": {
                  "type": "message",
                  "label": "action",
                  "text": "I would like to be a Sales Development Representative"
                },
                "contents": [
                  {
                    "type": "filler"
                  },
                  {
                    "type": "box",
                    "layout": "baseline",
                    "contents": [
                      {
                        "type": "filler"
                      },
                      {
                        "type": "text",
                        "text": "Let's Go",
                        "color": "#ffffff",
                        "flex": 0,
                        "offsetTop": "-2px"
                      },
                      {
                        "type": "filler"
                      }
                    ],
                    "spacing": "sm"
                  },
                  {
                    "type": "filler"
                  }
                ],
                "borderWidth": "1px",
                "cornerRadius": "4px",
                "spacing": "sm",
                "borderColor": "#ffffff",
                "margin": "xxl",
                "height": "40px"
              }
            ],
            "position": "absolute",
            "offsetBottom": "0px",
            "offsetStart": "0px",
            "offsetEnd": "0px",
            "paddingAll": "20px",
            "paddingTop": "18px",
            "backgroundColor": "#C2B28099" 
          }
        ],
        "paddingAll": "0px"
      }
    }
  ]
}